mc4/__init__.py
mc4/algorithm.py
mc4/command_line.py
mc4/utility.py
mc4-2.3.0.dist-info/LICENSE
mc4-2.3.0.dist-info/METADATA
mc4-2.3.0.dist-info/WHEEL
mc4-2.3.0.dist-info/entry_points.txt
mc4-2.3.0.dist-info/top_level.txt
mc4-2.3.0.dist-info/RECORD
