Metadata-Version: 2.1
Name: mc4
Version: 2.3.0
Summary: A python package for implementing Markov Chain Type 4 rank aggregation
Home-page: https://github.com/kalyaniuniversity/MC4
Author: Ayan Kumar Saha
Author-email: ayankumarsaha96@gmail.com
License: LICENSE
Project-URL: Full Documentation, https://github.com/kalyaniuniversity/MC4/wiki
Project-URL: Bug Reports, https://github.com/kalyaniuniversity/MC4/issues
Project-URL: Follow Author, https://github.com/Ayan-Kumar-Saha
Keywords: Machine Learning,Ranking,Markov Chain
Platform: UNKNOWN
Classifier: Programming Language :: Python :: 3
Classifier: Programming Language :: Python :: 3.6
Classifier: Programming Language :: Python :: 3.7
Classifier: Programming Language :: Python :: 3.8
Classifier: License :: OSI Approved :: GNU General Public License v3 (GPLv3)
Classifier: Operating System :: OS Independent
Requires-Python: >=3.6
Requires-Dist: numpy (>=1.19.0)
Requires-Dist: pandas (>=1.0.5)
